yatg/__init__.py
yatg/yatg.py
yatg-0.11.5.dist-info/LICENSE
yatg-0.11.5.dist-info/METADATA
yatg-0.11.5.dist-info/WHEEL
yatg-0.11.5.dist-info/entry_points.txt
yatg-0.11.5.dist-info/top_level.txt
yatg-0.11.5.dist-info/RECORD
