Metadata-Version: 2.1
Name: yatg
Version: 0.11.5
Summary: A utility for generating ASCII art table
Home-page: https://github.com/10gic/yatg
Author: cig01
Author-email: juhani@163.com
License: AGPLv3+
Platform: any
Classifier: Development Status :: 4 - Beta
Classifier: Environment :: Console
Classifier: Intended Audience :: Developers
Classifier: License :: OSI Approved :: GNU Affero General Public License v3 or later (AGPLv3+)
Classifier: Operating System :: OS Independent
Classifier: Programming Language :: Python
Classifier: Programming Language :: Python :: 2
Classifier: Programming Language :: Python :: 2.7
Classifier: Programming Language :: Python :: 3
Classifier: Programming Language :: Python :: 3.3
Classifier: Programming Language :: Python :: 3.4
Classifier: Programming Language :: Python :: 3.5
Classifier: Programming Language :: Python :: 3.6
Classifier: Programming Language :: Python :: 3.7
Classifier: Programming Language :: Python :: 3.8
Classifier: Topic :: Software Development :: Libraries :: Python Modules
Classifier: Topic :: Text Processing
Classifier: Topic :: Utilities
Provides-Extra: alignintty
Requires-Dist: blessed ; extra == 'alignintty'
Provides-Extra: forcewidth1
Requires-Dist: emoji ; extra == 'forcewidth1'
